.gitignore
LICENSE
MANIFEST.in
README.rst
setup.py
examples/simple_environment.py
examples/simple_vm_scale_set.py
examples/vm_scale_set_with_public_load_balancer.py
ionosphere/__init__.py
ionosphere/base.py
ionosphere/compute.py
ionosphere/constants.py
ionosphere/key_vault.py
ionosphere/managed_identity.py
ionosphere/network.py
ionosphere/storage.py
ionosphere/utils.py
ionosphere/validators.py
ionosphere.egg-info/PKG-INFO
ionosphere.egg-info/SOURCES.txt
ionosphere.egg-info/dependency_links.txt
ionosphere.egg-info/requires.txt
ionosphere.egg-info/top_level.txt
ionosphere/helpers/__init__.py
ionosphere/helpers/extensions.py
ionosphere/helpers/userdata.py
scripts/cfn
scripts/cfn2py