Metadata-Version: 2.1
Name: ionosphere
Version: 0.0.40
Summary: Azure Resource Manager Template creation library
Home-page: https://github.com/qualinext/ionosphere
Author: Alex Azarh
Author-email: alex.az@quali.com
License: New BSD license
Platform: UNKNOWN
Provides-Extra: policy
